test.py
hex_adder-0.1.0.dist-info/METADATA
hex_adder-0.1.0.dist-info/WHEEL
hex_adder-0.1.0.dist-info/entry_points.txt
hex_adder-0.1.0.dist-info/top_level.txt
hex_adder-0.1.0.dist-info/RECORD
