Metadata-Version: 2.1
Name: hex_adder
Version: 0.1.0
Summary: A simple Python package to add two numbers
Author: Your Name
Author-email: your.email@example.com
Classifier: Programming Language :: Python :: 3
Classifier: License :: OSI Approved :: MIT License
Classifier: Operating System :: OS Independent
Requires-Python: >=3.6
